toucan_data_sdk/__init__.py
toucan_data_sdk/fakir/__init__.py
toucan_data_sdk/fakir/fake_data_generator.py
toucan_data_sdk/fakir/predict_number_of_row_from_conf.py
toucan_data_sdk/py.typed
toucan_data_sdk/sdk.py
toucan_data_sdk/utils/__init__.py
toucan_data_sdk/utils/decorators.py
toucan_data_sdk/utils/generic/__init__.py
toucan_data_sdk/utils/generic/add_missing_row.py
toucan_data_sdk/utils/generic/clean.py
toucan_data_sdk/utils/generic/combine_columns_aggregation.py
toucan_data_sdk/utils/generic/compute_cumsum.py
toucan_data_sdk/utils/generic/compute_evolution.py
toucan_data_sdk/utils/generic/compute_ffill_by_group.py
toucan_data_sdk/utils/generic/date_requester.py
toucan_data_sdk/utils/generic/roll_up.py
toucan_data_sdk/utils/generic/two_values_melt.py
toucan_data_sdk/utils/helpers.py
toucan_data_sdk/utils/postprocess/__init__.py
toucan_data_sdk/utils/postprocess/add_aggregation_columns.py
toucan_data_sdk/utils/postprocess/argmax.py
toucan_data_sdk/utils/postprocess/categories_from_dates.py
toucan_data_sdk/utils/postprocess/converter.py
toucan_data_sdk/utils/postprocess/cumsum.py
toucan_data_sdk/utils/postprocess/fillna.py
toucan_data_sdk/utils/postprocess/filter.py
toucan_data_sdk/utils/postprocess/filter_by_date.py
toucan_data_sdk/utils/postprocess/groupby.py
toucan_data_sdk/utils/postprocess/if_else.py
toucan_data_sdk/utils/postprocess/json_to_table.py
toucan_data_sdk/utils/postprocess/linear_regression.py
toucan_data_sdk/utils/postprocess/math.py
toucan_data_sdk/utils/postprocess/melt.py
toucan_data_sdk/utils/postprocess/percentage.py
toucan_data_sdk/utils/postprocess/pivot.py
toucan_data_sdk/utils/postprocess/rank.py
toucan_data_sdk/utils/postprocess/rename.py
toucan_data_sdk/utils/postprocess/replace.py
toucan_data_sdk/utils/postprocess/sort.py
toucan_data_sdk/utils/postprocess/text.py
toucan_data_sdk/utils/postprocess/top.py
toucan_data_sdk/utils/postprocess/waterfall.py
toucan_data_sdk/utils/traceback.py
toucan_data_sdk-7.6.0.dist-info/LICENSE
toucan_data_sdk-7.6.0.dist-info/METADATA
toucan_data_sdk-7.6.0.dist-info/WHEEL
toucan_data_sdk-7.6.0.dist-info/RECORD
