Metadata-Version: 2.1
Name: toucan-data-sdk
Version: 7.6.0
Summary: Toucan data SDK
Home-page: https://github.com/ToucanToco/toucan-data-sdk
License: BSD-3-Clause
Author: Toucan Toco
Author-email: dev@toucantoco.com
Requires-Python: >=3.8,<4.0
Classifier: Intended Audience :: Developers
Classifier: License :: OSI Approved :: BSD License
Classifier: Programming Language :: Python :: 3
Classifier: Programming Language :: Python :: 3.8
Classifier: Programming Language :: Python :: 3.9
Classifier: Programming Language :: Python :: 3.10
Classifier: Programming Language :: Python :: 3.11
Classifier: Programming Language :: Python :: 3 :: Only
Classifier: Programming Language :: Python :: 3.10
Classifier: Programming Language :: Python :: 3.8
Classifier: Programming Language :: Python :: 3.9
Classifier: Typing :: Typed
Requires-Dist: engarde (>=0.4.0,<0.5.0)
Requires-Dist: joblib (>=1,<2)
Requires-Dist: pandas (>=1.4.1,<2.0.0)
Requires-Dist: python-slugify (>=5.0.2,<7.0.0)
Requires-Dist: tabulate (>=0.8.9,<0.10.0)
Requires-Dist: toucan-client (>=1.1.0,<2.0.0)
Project-URL: Documentation, https://toucantoco.github.io/toucan-data-sdk
Project-URL: Repository, https://github.com/ToucanToco/toucan-data-sdk
